clubscore/API.py
clubscore/__init__.py
clubscore/bot.py
clubscore/utils.py
clubscore/objects/CONTAINER.py
clubscore/objects/IMG.py
clubscore/objects/RECTANGLE.py
clubscore/objects/TEXT.py
clubscore/objects/__init__.py
clubscore-0.2.4.dist-info/LICENSE
clubscore-0.2.4.dist-info/METADATA
clubscore-0.2.4.dist-info/WHEEL
clubscore-0.2.4.dist-info/top_level.txt
clubscore-0.2.4.dist-info/RECORD
