Metadata-Version: 2.1
Name: clubscore
Version: 0.2.4
Summary: A package for creating customizable templates in XML
Home-page: https://github.com/davegimo/clubscore
Author: Davide Gimondo
Author-email: davegimo@gmail.com
License: MIT
Keywords: my-package,example,demo
Classifier: Development Status :: 3 - Alpha
Classifier: Intended Audience :: Developers
Classifier: License :: OSI Approved :: MIT License
Classifier: Programming Language :: Python :: 3
Classifier: Programming Language :: Python :: 3.6
Classifier: Programming Language :: Python :: 3.7
Classifier: Programming Language :: Python :: 3.8
Classifier: Programming Language :: Python :: 3.9
Classifier: Programming Language :: Python :: Implementation :: CPython
Classifier: Programming Language :: Python :: Implementation :: PyPy
Requires-Python: >=3.6, <4
License-File: LICENSE
Requires-Dist: beautifulsoup4
Requires-Dist: bs4
Requires-Dist: certifi
Requires-Dist: charset-normalizer
Requires-Dist: idna
Requires-Dist: Pillow
Requires-Dist: requests
Requires-Dist: soupsieve
Requires-Dist: urllib3
